{"wordCloud":[{"weight":50,"html":{"style":{"color":"#8d8989"}},"text":"love"},{"weight":34,"html":{"style":{"color":"#8d8989"}},"text":"inside coffee"},{"weight":30,"html":{"style":{"color":"#8d8989"}},"text":"inside place"},{"weight":28,"html":{"style":{"color":"#8d8989"}},"text":"leave"},{"weight":24,"html":{"style":{"color":"#8d8989"}},"text":"service coffee"},{"weight":24,"html":{"style":{"color":"#8d8989"}},"text":"bit"},{"weight":20,"html":{"style":{"color":"#8d8989"}},"text":"wedding place"},{"weight":20,"html":{"style":{"color":"#8d8989"}},"text":"try place"},{"weight":20,"html":{"style":{"color":"#8d8989"}},"text":"treat"},{"weight":18,"html":{"style":{"color":"#8d8989"}},"text":"start"},{"weight":18,"html":{"style":{"color":"#8d8989"}},"text":"look place"},{"weight":18,"html":{"style":{"color":"#8d8989"}},"text":"salad"},{"weight":16,"html":{"style":{"color":"#8d8989"}},"text":"shop coffee place"},{"weight":16,"html":{"style":{"color":"#8d8989"}},"text":"check"},{"weight":16,"html":{"style":{"color":"#8d8989"}},"text":"regular"},{"weight":16,"html":{"style":{"color":"#8d8989"}},"text":"staff place"},{"weight":16,"html":{"style":{"color":"#8d8989"}},"text":"review place"},{"weight":14,"html":{"style":{"color":"#8d8989"}},"text":"weekend"},{"weight":14,"html":{"style":{"color":"#8d8989"}},"text":"morning"},{"weight":14,"html":{"style":{"color":"#8d8989"}},"text":"tea place"},{"weight":14,"html":{"style":{"color":"#8d8989"}},"text":"wedding coffee"},{"weight":14,"html":{"style":{"color":"#8d8989"}},"text":"latte"},{"weight":14,"html":{"style":{"color":"#8d8989"}},"text":"studio class yoga"},{"weight":14,"html":{"style":{"color":"#8d8989"}},"text":"plan"},{"weight":14,"html":{"style":{"color":"#8d8989"}},"text":"taste"},{"weight":14,"html":{"style":{"color":"#8d8989"}},"text":"year place"},{"weight":14,"html":{"style":{"color":"#8d8989"}},"text":"husband"},{"weight":14,"html":{"style":{"color":"#8d8989"}},"text":"class yoga place"},{"weight":14,"html":{"style":{"color":"#8d8989"}},"text":"studio patio yoga"},{"weight":12,"html":{"style":{"color":"#8d8989"}},"text":"day coffee"},{"weight":12,"html":{"style":{"color":"#8d8989"}},"text":"owner coffee"},{"weight":12,"html":{"style":{"color":"#8d8989"}},"text":"customer owner place"},{"weight":12,"html":{"style":{"color":"#8d8989"}},"text":"sign"},{"weight":12,"html":{"style":{"color":"#8d8989"}},"text":"inside lunch"},{"weight":12,"html":{"style":{"color":"#8d8989"}},"text":"class yoga coffee"},{"weight":12,"html":{"style":{"color":"#8d8989"}},"text":"mocha"},{"weight":12,"html":{"style":{"color":"#8d8989"}},"text":"family"},{"weight":12,"html":{"style":{"color":"#8d8989"}},"text":"atmosphere food"},{"weight":12,"html":{"style":{"color":"#8d8989"}},"text":"house coffee place"},{"weight":12,"html":{"style":{"color":"#8d8989"}},"text":"return"},{"weight":12,"html":{"style":{"color":"#8d8989"}},"text":"house patio coffee"},{"weight":12,"html":{"style":{"color":"#8d8989"}},"text":"cup coffee"},{"weight":12,"html":{"style":{"color":"#8d8989"}},"text":"look owner"},{"weight":12,"html":{"style":{"color":"#8d8989"}},"text":"yoga coffee place"},{"weight":12,"html":{"style":{"color":"#8d8989"}},"text":"change"},{"weight":12,"html":{"style":{"color":"#8d8989"}},"text":"spot place"},{"weight":12,"html":{"style":{"color":"#8d8989"}},"text":"couple"},{"weight":10,"html":{"style":{"color":"#8d8989"}},"text":"patio coffee place"},{"weight":10,"html":{"style":{"color":"#8d8989"}},"text":"online"},{"weight":10,"html":{"style":{"color":"#8d8989"}},"text":"kind coffee"}]}