{"wordCloud":[{"weight":50,"html":{"style":{"color":"#d01919"}},"text":"bagel"},{"weight":50,"html":{"style":{"color":"#d01919"}},"text":"cheese"},{"weight":50,"html":{"style":{"color":"#d01919"}},"text":"cream cheese bagel"},{"weight":40,"html":{"style":{"color":"#d01919"}},"text":"work"},{"weight":38,"html":{"style":{"color":"#d01919"}},"text":"sandwich cheese bagel"},{"weight":34,"html":{"style":{"color":"#d01919"}},"text":"way"},{"weight":34,"html":{"style":{"color":"#d01919"}},"text":"cream sandwich cheese"},{"weight":32,"html":{"style":{"color":"#d01919"}},"text":"cream sandwich bagel"},{"weight":30,"html":{"style":{"color":"#d01919"}},"text":"special bagel"},{"weight":30,"html":{"style":{"color":"#d01919"}},"text":"order cheese bagel"},{"weight":30,"html":{"style":{"color":"#d01919"}},"text":"egg sandwich bagel"},{"weight":28,"html":{"style":{"color":"#d01919"}},"text":"order cream cheese"},{"weight":26,"html":{"style":{"color":"#d01919"}},"text":"way bagel"},{"weight":26,"html":{"style":{"color":"#d01919"}},"text":"order cream bagel"},{"weight":24,"html":{"style":{"color":"#d01919"}},"text":"egg cheese bagel"},{"weight":22,"html":{"style":{"color":"#d01919"}},"text":"work bagel"},{"weight":22,"html":{"style":{"color":"#d01919"}},"text":"place sandwich bagel"},{"weight":22,"html":{"style":{"color":"#d01919"}},"text":"time cheese bagel"},{"weight":22,"html":{"style":{"color":"#d01919"}},"text":"place cheese bagel"},{"weight":22,"html":{"style":{"color":"#d01919"}},"text":"place cream cheese"},{"weight":22,"html":{"style":{"color":"#d01919"}},"text":"breakfast sandwich bagel"},{"weight":22,"html":{"style":{"color":"#d01919"}},"text":"order sandwich bagel"},{"weight":20,"html":{"style":{"color":"#d01919"}},"text":"service cream cheese"},{"weight":20,"html":{"style":{"color":"#d01919"}},"text":"quality bagel"},{"weight":20,"html":{"style":{"color":"#d01919"}},"text":"time cream cheese"},{"weight":20,"html":{"style":{"color":"#d01919"}},"text":"place cream bagel"},{"weight":20,"html":{"style":{"color":"#d01919"}},"text":"style bagel"},{"weight":18,"html":{"style":{"color":"#d01919"}},"text":"taste bagel"},{"weight":18,"html":{"style":{"color":"#d01919"}},"text":"hand bagel"},{"weight":18,"html":{"style":{"color":"#d01919"}},"text":"people cream cheese"},{"weight":18,"html":{"style":{"color":"#d01919"}},"text":"time cream bagel"},{"weight":18,"html":{"style":{"color":"#d01919"}},"text":"wait order bagel"},{"weight":18,"html":{"style":{"color":"#d01919"}},"text":"order service bagel"},{"weight":18,"html":{"style":{"color":"#d01919"}},"text":"egg cream cheese"},{"weight":18,"html":{"style":{"color":"#d01919"}},"text":"wait sandwich bagel"},{"weight":18,"html":{"style":{"color":"#d01919"}},"text":"egg cream bagel"},{"weight":18,"html":{"style":{"color":"#d01919"}},"text":"service sandwich bagel"},{"weight":18,"html":{"style":{"color":"#d01919"}},"text":"day bagel"},{"weight":18,"html":{"style":{"color":"#d01919"}},"text":"service cheese bagel"},{"weight":18,"html":{"style":{"color":"#d01919"}},"text":"look bagel"},{"weight":18,"html":{"style":{"color":"#d01919"}},"text":"spread bagel"},{"weight":18,"html":{"style":{"color":"#d01919"}},"text":"service cream bagel"},{"weight":16,"html":{"style":{"color":"#d01919"}},"text":"order time bagel"},{"weight":16,"html":{"style":{"color":"#d01919"}},"text":"flavor"},{"weight":16,"html":{"style":{"color":"#d01919"}},"text":"egg sandwich cheese"},{"weight":16,"html":{"style":{"color":"#d01919"}},"text":"toast cream cheese"},{"weight":16,"html":{"style":{"color":"#d01919"}},"text":"people cream bagel"},{"weight":16,"html":{"style":{"color":"#d01919"}},"text":"toast cheese bagel"},{"weight":16,"html":{"style":{"color":"#d01919"}},"text":"people cheese bagel"},{"weight":16,"html":{"style":{"color":"#d01919"}},"text":"visit bagel"}]}